{"assets/card_bg.png":["assets/card_bg.png"],"assets/default_avatar.png":["assets/default_avatar.png"],"assets/dhl.png":["assets/dhl.png"],"assets/fonts/Gelasio_Bold.ttf":["assets/fonts/Gelasio_Bold.ttf"],"assets/fonts/Gelasio_Medium.ttf":["assets/fonts/Gelasio_Medium.ttf"],"assets/fonts/Gelasio_Regular.ttf":["assets/fonts/Gelasio_Regular.ttf"],"assets/fonts/Gelasio_SemiBold.ttf":["assets/fonts/Gelasio_SemiBold.ttf"],"assets/fonts/Merriweather_Bold.ttf":["assets/fonts/Merriweather_Bold.ttf"],"assets/fonts/Merriweather_Regular.ttf":["assets/fonts/Merriweather_Regular.ttf"],"assets/fonts/NunitoSans_Bold.ttf":["assets/fonts/NunitoSans_Bold.ttf"],"assets/fonts/NunitoSans_ExtraBold.ttf":["assets/fonts/NunitoSans_ExtraBold.ttf"],"assets/fonts/NunitoSans_Light.ttf":["assets/fonts/NunitoSans_Light.ttf"],"assets/fonts/NunitoSans_Regular.ttf":["assets/fonts/NunitoSans_Regular.ttf"],"assets/fonts/NunitoSans_SemiBold.ttf":["assets/fonts/NunitoSans_SemiBold.ttf"],"assets/furniture_loading.gif":["assets/furniture_loading.gif"],"assets/furniture_vector.svg":["assets/furniture_vector.svg"],"assets/icons/armchair_icon.svg":["assets/icons/armchair_icon.svg"],"assets/icons/bed_icon.svg":["assets/icons/bed_icon.svg"],"assets/icons/cart_icon.svg":["assets/icons/cart_icon.svg"],"assets/icons/cart_icon_grey.svg":["assets/icons/cart_icon_grey.svg"],"assets/icons/chair_icon.svg":["assets/icons/chair_icon.svg"],"assets/icons/edit_icon.svg":["assets/icons/edit_icon.svg"],"assets/icons/favorite_icon.svg":["assets/icons/favorite_icon.svg"],"assets/icons/favorite_icon_black.svg":["assets/icons/favorite_icon_black.svg"],"assets/icons/favorite_selected_icon.svg":["assets/icons/favorite_selected_icon.svg"],"assets/icons/home_icon.svg":["assets/icons/home_icon.svg"],"assets/icons/home_selected_icon.svg":["assets/icons/home_selected_icon.svg"],"assets/icons/lamp_icon.svg":["assets/icons/lamp_icon.svg"],"assets/icons/logout_icon.svg":["assets/icons/logout_icon.svg"],"assets/icons/mastercard.svg":["assets/icons/mastercard.svg"],"assets/icons/mastercard_bw.svg":["assets/icons/mastercard_bw.svg"],"assets/icons/notification_icon.svg":["assets/icons/notification_icon.svg"],"assets/icons/notification_selected_icon.svg":["assets/icons/notification_selected_icon.svg"],"assets/icons/password_visible.svg":["assets/icons/password_visible.svg"],"assets/icons/person_icon.svg":["assets/icons/person_icon.svg"],"assets/icons/person_selected_icon.svg":["assets/icons/person_selected_icon.svg"],"assets/icons/popular_icon.svg":["assets/icons/popular_icon.svg"],"assets/icons/search_icon.svg":["assets/icons/search_icon.svg"],"assets/icons/search_icon_grey.svg":["assets/icons/search_icon_grey.svg"],"assets/icons/shopping_bag_icon.svg":["assets/icons/shopping_bag_icon.svg"],"assets/icons/shopping_bag_icon_black.svg":["assets/icons/shopping_bag_icon_black.svg"],"assets/icons/star_icon.svg":["assets/icons/star_icon.svg"],"assets/icons/table_icon.svg":["assets/icons/table_icon.svg"],"assets/icons/visacard.svg":["assets/icons/visacard.svg"],"assets/lottie/splash_loading_animation.json":["assets/lottie/splash_loading_animation.json"],"assets/onBoarding.png":["assets/onBoarding.png"],"assets/order_success.svg":["assets/order_success.svg"],"assets/sample.png":["assets/sample.png"],"packages/fluttertoast/assets/toastify.css":["packages/fluttertoast/assets/toastify.css"],"packages/fluttertoast/assets/toastify.js":["packages/fluttertoast/assets/toastify.js"]}